{
  "content": [
    {
      "@id": "1",
      "caseId": "19221de9-f749-48d1-9edb-629c467a887d",
      "lid": "4a704d21-a872-4a62-a7f9-764fc7ab0ed7",
      "idx": "1",
      "caseStatusDb": 45,
      "caseStatus": "已预约",
      "caseNodeDb": 5,
      "caseNode": "摇号",
      "lotteryStatusDb": 5,
      "lotteryStatus": "已预约",
      "updateDttm": 1578270030000,
      "jdNo": "(2020)陕05鉴3号",
      "caseTypeDb": 1,
      "caseType": "鉴定委托",
      "isParty": true,
      "isAgain": false,
      "isTrial": false,
      "caseSource": "审判系统",
      "plaintiff": "申请执行人：任毅，居民身份证：0，手机号码：15009268220，\r\n被执行人：李峰，居民身份证：612103197302111518，手机号码：13571527622，\r\n",
      "caseNo": "(2019)陕0582执259号",
      "courtApply": "R53",
      "courtNameApply": "华阴市人民法院",
      "courtAccept": "R50",
      "courtNameAccept": "渭南市中级人民法院",
      "courtLxdhAccept": "0913-2117521",
      "bafg": "姜勇",
      "bafgId": "365101029",
      "zbr": "曹晓",
      "zbrId": "364801119",
      "ay": "借款合同纠纷",
      "closeTypeDisplay": "",
      "jdlbId": "10",
      "jdlb": "房地产评估",
      "jdlbId0": 5,
      "jdlb0": "评估",
      "rollMode": -1,
      "reasonAppoint": "",
      "dateApply": 1575993600000,
      "dateRegister": 1575993600000,
      "dateAccept": 1578269752000,
      "dateSetperson": 1578240000000
    },
    {
      "@id": "2",
      "caseId": "ed72a927-9276-4d4d-80c8-1a2142b260ca",
      "lid": "385a2e84-d392-4035-aa78-f71b8be345f9",
      "idx": "1",
      "caseStatusDb": 45,
      "caseStatus": "已预约",
      "caseNodeDb": 5,
      "caseNode": "摇号",
      "lotteryStatusDb": 5,
      "lotteryStatus": "已预约",
      "updateDttm": 1546421739000,
      "jdNo": "(2019)陕05鉴7号",
      "caseTypeDb": 1,
      "caseType": "鉴定委托",
      "isParty": true,
      "isAgain": false,
      "isTrial": true,
      "caseSource": "审判系统",
      "plaintiff": "申请执行人：临渭区海博小额贷款有限责任公司，组织机构代码：91610502567121444P，手机号码：18991636930，\r\n被执行人：张小龙，居民身份证：610502197410165031，手机号码：18709139999，\r\n被执行人：赵媛娃，居民身份证：610502197507055023，手机号码：18709132001，\r\n",
      "caseNo": "(2018)陕0502执恢365号",
      "courtApply": "R51",
      "courtNameApply": "渭南市临渭区人民法院",
      "courtAccept": "R50",
      "courtNameAccept": "渭南市中级人民法院",
      "courtLxdhAccept": "0913-2117521",
      "bafg": "刘晓静",
      "bafgId": "364901033",
      "zbr": "李永峰",
      "zbrId": "364801101",
      "ay": "借款合同纠纷",
      "closeTypeDisplay": "",
      "jdlbId": "10",
      "jdlb": "房地产评估",
      "jdlbId0": 5,
      "jdlb0": "评估",
      "rollMode": -1,
      "reasonAppoint": "",
      "dateApply": 1545753600000,
      "dateRegister": 1545753600000,
      "dateAccept": 1546387712000,
      "dateSetperson": 1546358400000
    },
    {
      "@id": "3",
      "caseId": "8145ea45-2ddb-48f2-b788-5f31d41a2fcc",
      "lid": "ae9cc449-ad6d-448c-999d-de6328492a58",
      "idx": "1",
      "caseStatusDb": 45,
      "caseStatus": "已预约",
      "caseNodeDb": 5,
      "caseNode": "摇号",
      "lotteryStatusDb": 5,
      "lotteryStatus": "已预约",
      "updateDttm": 1576456463000,
      "jdNo": "(2019)陕05鉴1196号",
      "caseTypeDb": 1,
      "caseType": "鉴定委托",
      "isParty": false,
      "isAgain": false,
      "isTrial": false,
      "caseSource": "审判系统",
      "plaintiff": "被告|被执行人：刘洋，居民身份证：610502199405066820，联系电话：17719752933\r\n原告|申请执行人：中国农业银行股份有限公司渭南朝阳路支行，组织机构代码：0，联系电话：13571381788\r\n",
      "caseNo": "(2019)陕0502执1624号",
      "courtApply": "R51",
      "courtNameApply": "渭南市临渭区人民法院",
      "courtAccept": "R50",
      "courtNameAccept": "渭南市中级人民法院",
      "courtLxdhAccept": "0913-2117521",
      "bafg": "田剑桥",
      "bafgId": "364901108",
      "zbr": "张方舟",
      "zbrId": "364801689",
      "ay": "借款合同纠纷",
      "closeTypeDisplay": "",
      "jdlbId": "10",
      "jdlb": "房地产评估",
      "jdlbId0": 5,
      "jdlb0": "评估",
      "rollMode": -1,
      "reasonAppoint": "",
      "dateApply": 1576080000000,
      "dateRegister": 1576080000000,
      "dateAccept": 1576454203000,
      "dateSetperson": 1576425600000
    },
    {
      "@id": "4",
      "caseId": "1fba93f4-38c8-4582-8a1f-526a8182af19",
      "lid": "af9b6a73-f30a-4ad9-8882-e1caf4176722",
      "idx": "1",
      "caseStatusDb": 60,
      "caseStatus": "待审批",
      "caseNodeDb": 6,
      "caseNode": "结案审批",
      "lotteryStatusDb": 5,
      "lotteryStatus": "已预约",
      "updateDttm": 1576749901000,
      "jdNo": "(2019)陕04鉴1206号",
      "caseTypeDb": 1,
      "caseType": "鉴定委托",
      "isParty": true,
      "isAgain": false,
      "isTrial": tr
      2020-03-25
      10: 58
      :
      43.845
      16277-16371/com.unicorn.forensic2
      D/OkHttp: n
      ":1574179200000,"
      dateFinishRequest
      ":1574179200000},{"
      @id
      ":"
      5
      ","
      caseId
      ":"
      463eb844-82fa-41bf-aff9-946d7a3eabf5
      ","
      lid
      ":"
      32a07441-830f-4702-84b7-af6babe3e268
      ","
      idx
      ":"
      1
      ","
      caseStatusDb
      ":45,"
      caseStatus
      ":"
      已预约
      ","
      caseNodeDb
      ":5,"
      caseNode
      ":"
      摇号
      ","
      lotteryStatusDb
      ":5,"
      lotteryStatus
      ":"
      已预约
      ","
      updateDttm
      ":1578638711000,"
      jdNo
      ":"
      (2020)陕0825鉴5号
      ","
      caseTypeDb
      ":1,"
      caseType
      ":"
      鉴定委托
      ","
      isParty
      ":true,"
      isAgain
      ":false,"
      isTrial
      ":true,"
      caseSource
      ":"
      审判系统
      ","
      plaintiff
      ":"
      原告
      ：
      定边县金天利房地产投资有限责任公司
      ，
      组织机构代码
      ：
      916108252241229712
      ，
      手机号码
      ：
      13488022888
      ，
      \
      r
      \
      n被告
      ：
      田亚芳
      ，
      居民身份证
      ：
      612726196806250047
      ，
      手机号码
      ：
      13220022162
      ，
      \
      r
      \
      n被告
      ：
      田亚芸
      ，
      居民身份证
      ：
      612726197102160064
      ，
      手机号码
      ：
      13038969996
      ，
      \
      r
      \
      n被告
      ：
      田亚妮
      ，
      居民身份证
      ：
      612726197606260026
      ，
      手机号码
      ：
      13038994449
      ，
      \
      r
      \
      n
      ","
      caseNo
      ":"
      (2019)陕0825民初7266号
      ","
      courtApply
      ":"
      RA6
      ","
      courtNameApply
      ":"
      定边县人民法院
      ","
      courtAccept
      ":"
      RA6
      ","
      courtNameAccept
      ":"
      定边县人民法院
      ","
      courtLxdhAccept
      ":"
      ","
      bafg
      ":"
      党翠琴
      ","
      bafgId
      ":"
      371101084
      ","
      zbr
      ":"
      赵凤义
      ","
      zbrId
      ":"
      371101022
      ","
      ay
      ":"
      商品房预售合同纠纷
      ","
      closeTypeDisplay
      ":"
      ","
      jdlbId
      ":"
      30
      ","
      jdlb
      ":"
      价格鉴证
      ","
      jdlbId0
      ":5,"
      jdlb0
      ":"
      评估
      ","
      rollMode
      ":-1,"
      reasonAppoint
      ":"
      ","
      dateApply
      ":1578585600000,"
      dateRegister
      ":1578585600000,"
      dateAccept
      ":1578638159000,"
      dateSetperson
      ":1578585600000}],"
      pageable
      ":{"
      sort
      ":{"
      sorted
      ":true,"
      unsorted
      ":false,"
      empty
      ":false},"
      offset
      ":"
      0
      ","
      pageSize
      ":5,"
      pageNumber
      ":0,"
      unpaged
      ":false,"
      paged
      ":true},"
      last
      ":false,"
      totalElements
      ":"
      28196
      ","
      totalPages
      ":5640,"
      number
      ":0,"
      size
      ":5,"
      sort
      ":{"
      sorted
      ":true,"
      unsorted
      ":false,"
      empty
      ":false},"
      first
      ":true,"
      numberOfElements
      ":5,"
      empty
      ":false}